j2v/__init__.py
j2v/generation/__init__.py
j2v/generation/generator.py
j2v/generation/processor.py
j2v/generation/result_writer.py
j2v/str_templates/__init__.py
j2v/str_templates/looker_templates.py
j2v/str_templates/sql_templates.py
j2v/tests/__init__.py
j2v/tests/test_generator.py
j2v/tests/test_helpers.py
j2v/utils/__init__.py
j2v/utils/config.py
j2v/utils/config.yml
j2v/utils/helpers.py
j2v-1.6.0.dist-info/LICENSE
j2v-1.6.0.dist-info/METADATA
j2v-1.6.0.dist-info/WHEEL
j2v-1.6.0.dist-info/top_level.txt
j2v-1.6.0.dist-info/RECORD
