Metadata-Version: 2.1
Name: j2v
Version: 1.6.0
Summary: A tool to generate Looker views and explores from JSONs
Home-page: https://github.com/Cimpress-MCP/j2v
Author: CIMBA - Cimpress Technology
Author-email: cimba@cimpress.com
License: UNKNOWN
Platform: UNKNOWN
Classifier: Programming Language :: Python :: 3
Classifier: License :: OSI Approved :: Apache Software License
Classifier: Operating System :: OS Independent
Requires-Python: >=3
Requires-Dist: PyYAML (>=5.1)
